nebulatk/__init__.py
nebulatk/animation_controller.py
nebulatk/bounds_manager.py
nebulatk/colors_manager.py
nebulatk/defaults.py
nebulatk/fonts_manager.py
nebulatk/image_manager.py
nebulatk/nebulatk.py
nebulatk/standard_methods.py
nebulatk/taskbar_manager.py
nebulatk/examples/example.py
nebulatk/widgets/__init__.py
nebulatk/widgets/base.py
nebulatk/widgets/button.py
nebulatk/widgets/container.py
nebulatk/widgets/entry.py
nebulatk/widgets/frame.py
nebulatk/widgets/label.py
nebulatk/widgets/slider.py
nebulatk-0.2.1.4.dist-info/METADATA
nebulatk-0.2.1.4.dist-info/WHEEL
nebulatk-0.2.1.4.dist-info/top_level.txt
nebulatk-0.2.1.4.dist-info/RECORD
