Metadata-Version: 2.4
Name: nebulatk
Version: 0.2.1.4
Summary: Improved tkinter-style gui system.
Author-email: Control-Alt-OP <ctrl.alt.op@gmail.com>
Project-URL: Homepage, https://github.com/CTRL-ALT-OP/nebulatk
Keywords: tcl,tkinter,nebulatk,gui,transparency
Classifier: Programming Language :: Python
Classifier: Programming Language :: Python :: 3
Requires-Python: >=3.9
Requires-Dist: pillow
Requires-Dist: tk
